ka_uts_prc/__init__.py
ka_uts_prc/__version__.py
ka_uts_prc/prc.py
ka_uts_prc/py.typed
ka_uts_prc-4.1.0.250525.dist-info/licenses/LICENSE.txt
ka_uts_prc-4.1.0.250525.dist-info/METADATA
ka_uts_prc-4.1.0.250525.dist-info/WHEEL
ka_uts_prc-4.1.0.250525.dist-info/top_level.txt
ka_uts_prc-4.1.0.250525.dist-info/RECORD
